inverterd/__init__.py
inverterd/inverterd.py
inverterd-1.0.3.dist-info/LICENSE
inverterd-1.0.3.dist-info/METADATA
inverterd-1.0.3.dist-info/WHEEL
inverterd-1.0.3.dist-info/top_level.txt
inverterd-1.0.3.dist-info/RECORD
