Metadata-Version: 2.1
Name: inverterd
Version: 1.0.3
Summary: UNKNOWN
Home-page: https://github.com/gch1p/inverterd-client.git
Author: Evgeny Zinoviev
Author-email: me@ch1p.io
License: MIT
Project-URL: Bug Tracker, https://github.com/gch1p/inverterd-client/issues
Platform: UNKNOWN
Classifier: Programming Language :: Python :: 3
Classifier: License :: OSI Approved :: MIT License
Classifier: Operating System :: OS Independent
Requires-Python: >=3.6
